[
	{
		"index": 0,
		"data": [
			{
				"from": "Genesis Block",
				"to": "Genesis Block",
				"amount": 0,
				"timestamp": 1529519032082,
				"hash": "ff6447c052e677e91e376175edeb8c51"
			}
		],
		"previousHash": "",
		"timestamp": 1529519032083,
		"nonce": 0,
		"hash": "77696d06de2d25ef4e33d6a05425738d"
	},
	{
		"index": 1,
		"data": [
			{
				"from": "iih0tUtSXfVkqfPD",
				"to": "2tEaC8OHn4Mz6DdS",
				"amount": 2669,
				"timestamp": 1529519035203,
				"hash": "ff680bdf1b7c299244a0d93deb4ef869"
			}
		],
		"previousHash": "77696d06de2d25ef4e33d6a05425738d",
		"timestamp": 1529519035204,
		"nonce": 3510,
		"hash": "00008befb6814bb75f17765a531fdee3"
	},
	{
		"index": 2,
		"data": [
			{
				"from": "A9SYBfD1BDeFeyLR",
				"to": "YAqYrArsk5XgVkUh",
				"amount": 2285,
				"timestamp": 1529519035308,
				"hash": "8c7fa39bb574e103feac5ed26b4cd542"
			}
		],
		"previousHash": "00008befb6814bb75f17765a531fdee3",
		"timestamp": 1529519035308,
		"nonce": 29163,
		"hash": "0000e9559422a203d5a7051967c52b80"
	},
	{
		"index": 3,
		"data": [
			{
				"from": "x3ZU7N1H39ap5g2i",
				"to": "l1L7XkLaoiYUiSig",
				"amount": 2716,
				"timestamp": 1529519036020,
				"hash": "7a744d271ef742ca2fae3474be35415c"
			}
		],
		"previousHash": "0000e9559422a203d5a7051967c52b80",
		"timestamp": 1529519036020,
		"nonce": 4966,
		"hash": "00004a175db474155d9ab653fe1cb0d2"
	},
	{
		"index": 4,
		"data": [
			{
				"from": "VLgy16QpEH1dIftI",
				"to": "Zvt2suhYiuCxmQpV",
				"amount": 5288,
				"timestamp": 1529519036184,
				"hash": "4b4ccd136ab22079228ffe478c0ef10e"
			}
		],
		"previousHash": "00004a175db474155d9ab653fe1cb0d2",
		"timestamp": 1529519036184,
		"nonce": 134842,
		"hash": "00006a9f732012172a933d6ced8ebbba"
	},
	{
		"index": 5,
		"data": [
			{
				"from": "NjaZSQhvix6U1zmZ",
				"to": "nlJqTG7CUtHLwo1c",
				"amount": 2032,
				"timestamp": 1529519038153,
				"hash": "1ac6adaeed909c5b48826fcf0669aa23"
			}
		],
		"previousHash": "00006a9f732012172a933d6ced8ebbba",
		"timestamp": 1529519038153,
		"nonce": 31236,
		"hash": "0000a354cd6b775d7ad2833f5261e157"
	},
	{
		"index": 6,
		"data": [
			{
				"from": "sOcv62YyxVMhjYQu",
				"to": "G6AkmQkbkVLH2SN0",
				"amount": 9566,
				"timestamp": 1529519051873,
				"hash": "834742df4c4e9aec3052793c5921c162"
			}
		],
		"previousHash": "0000a354cd6b775d7ad2833f5261e157",
		"timestamp": 1529519051873,
		"nonce": 92294,
		"hash": "00008f9e392c3fad5d48eb452a7e0a7f"
	},
	{
		"index": 7,
		"data": [
			{
				"from": "v6tJuooCOzZQIQV3",
				"to": "j34SaZiKSJdpmyRN",
				"amount": 9723,
				"timestamp": 1529519053138,
				"hash": "62c17cdaf17ca3d8e51842dcdc713026"
			}
		],
		"previousHash": "00008f9e392c3fad5d48eb452a7e0a7f",
		"timestamp": 1529519053138,
		"nonce": 14716,
		"hash": "00005a2fa9cdc02b5558287e57ee59c7"
	},
	{
		"index": 8,
		"data": [
			{
				"from": "2QCbUYdIXCrAGWhd",
				"to": "3jcZOD7CZMCaZhzj",
				"amount": 3041,
				"timestamp": 1529519053367,
				"hash": "31a42103deeb41b3b8d2afc6c1bcf981"
			}
		],
		"previousHash": "00005a2fa9cdc02b5558287e57ee59c7",
		"timestamp": 1529519053367,
		"nonce": 15641,
		"hash": "0000d48618f6c4a57b74eec639375ac6"
	},
	{
		"index": 9,
		"data": [
			{
				"from": "IOYxBTnTRgaU5Tjp",
				"to": "0bDBeYgTXl9GC3mE",
				"amount": 3773,
				"timestamp": 1529519053636,
				"hash": "b992588d365077b08b70f0a2ac233b1b"
			}
		],
		"previousHash": "0000d48618f6c4a57b74eec639375ac6",
		"timestamp": 1529519053636,
		"nonce": 60758,
		"hash": "000025ca362d4124b1fd561346fe1d43"
	},
	{
		"index": 10,
		"data": [
			{
				"from": "QHYH0tj06n7pG3eG",
				"to": "B2frAceRQTcssS46",
				"amount": 9480,
				"timestamp": 1529519054583,
				"hash": "4440222df0e0f4a27eca2105b25fc664"
			}
		],
		"previousHash": "000025ca362d4124b1fd561346fe1d43",
		"timestamp": 1529519054583,
		"nonce": 1260,
		"hash": "000095610335bc5fc2b24ba730d7c774"
	},
	{
		"index": 11,
		"data": [
			{
				"from": "nIIIg362xrj2ZJN9",
				"to": "OPPPIwfD85AAi5oc",
				"amount": 3988,
				"timestamp": 1529519054628,
				"hash": "cb8e670bb3d4750f88eec663711aa47e"
			}
		],
		"previousHash": "000095610335bc5fc2b24ba730d7c774",
		"timestamp": 1529519054628,
		"nonce": 87675,
		"hash": "00005d0cf227ab3444a829acf7f9242b"
	},
	{
		"index": 12,
		"data": [
			{
				"from": "SlDPxXj2IXooqcIq",
				"to": "1f8D8HzPZzR00mZq",
				"amount": 6476,
				"timestamp": 1529519055999,
				"hash": "9b2c15dd7bffd4caefc31a0805f77a69"
			}
		],
		"previousHash": "00005d0cf227ab3444a829acf7f9242b",
		"timestamp": 1529519055999,
		"nonce": 133452,
		"hash": "0000d82e67d8a5be749346cd50098d09"
	},
	{
		"index": 13,
		"data": [
			{
				"from": "KKahOaNkpG71RqTz",
				"to": "U4uRoqHIixhxNDVX",
				"amount": 2178,
				"timestamp": 1529519057960,
				"hash": "a8fa87da5dbb5cd69fb7e7c1ec970a4e"
			}
		],
		"previousHash": "0000d82e67d8a5be749346cd50098d09",
		"timestamp": 1529519057960,
		"nonce": 155346,
		"hash": "0000f25e539c1cbd1d3be4f264a047a0"
	},
	{
		"index": 14,
		"data": [
			{
				"from": "kHQsI4JtuDuuJolI",
				"to": "Yaq0FGn8GpKB6YGz",
				"amount": 904,
				"timestamp": 1529519060209,
				"hash": "28fda11af4410190c8ef5c8fc62215a8"
			}
		],
		"previousHash": "0000f25e539c1cbd1d3be4f264a047a0",
		"timestamp": 1529519060210,
		"nonce": 90036,
		"hash": "0000b9bb3cb4fd8817fa7edd4bf73eed"
	},
	{
		"index": 15,
		"data": [
			{
				"from": "gWNFGwwJJRchDLoe",
				"to": "Lns9n3bKJoZClrHg",
				"amount": 1028,
				"timestamp": 1529519061595,
				"hash": "db50ff0e37e18343c0dd37d0d080a01f"
			}
		],
		"previousHash": "0000b9bb3cb4fd8817fa7edd4bf73eed",
		"timestamp": 1529519061596,
		"nonce": 70915,
		"hash": "00005b3ad87f51eb1fe84845d7e57e1a"
	},
	{
		"index": 16,
		"data": [
			{
				"from": "kflh5iDR67cz1fW6",
				"to": "nisW0pttHfzNGrZ5",
				"amount": 7788,
				"timestamp": 1529519062729,
				"hash": "0b77e2f03f3af5d26ae9a0571cc8bfff"
			}
		],
		"previousHash": "00005b3ad87f51eb1fe84845d7e57e1a",
		"timestamp": 1529519062729,
		"nonce": 35287,
		"hash": "00004fabf0a4899d10991910cbc1e060"
	},
	{
		"index": 17,
		"data": [
			{
				"from": "z5yVUC2iQ11PTKzR",
				"to": "r1HCb5oCfE43cOGT",
				"amount": 5004,
				"timestamp": 1529519063363,
				"hash": "41e2273cebe2a0f0529375599b85740c"
			}
		],
		"previousHash": "00004fabf0a4899d10991910cbc1e060",
		"timestamp": 1529519063364,
		"nonce": 5991,
		"hash": "0000e0c2566af13d980bc877476c45e8"
	},
	{
		"index": 18,
		"data": [
			{
				"from": "R096R5BdKcHVs7Ig",
				"to": "DQptQ6fnBC0HDP8s",
				"amount": 401,
				"timestamp": 1529519063465,
				"hash": "d3facc76baf98e42586f440b8db6e2b2"
			}
		],
		"previousHash": "0000e0c2566af13d980bc877476c45e8",
		"timestamp": 1529519063465,
		"nonce": 35017,
		"hash": "0000df3261d9c860ac27be460bc2831a"
	},
	{
		"index": 19,
		"data": [
			{
				"from": "mv2ypJET6biACFBh",
				"to": "xZw1jFz3JuHCD1HP",
				"amount": 3393,
				"timestamp": 1529519064091,
				"hash": "0f735140a57ca4e2baf9f9d8976d2c99"
			}
		],
		"previousHash": "0000df3261d9c860ac27be460bc2831a",
		"timestamp": 1529519064091,
		"nonce": 8202,
		"hash": "00007e8977c7a5ffc47de7f4b2951531"
	},
	{
		"index": 20,
		"data": [
			{
				"from": "t1db8CqQzSrjGhoB",
				"to": "qy9z1LizNlCIqymi",
				"amount": 2332,
				"timestamp": 1529519064246,
				"hash": "322af7c848c6cbd608ca26dc89114898"
			}
		],
		"previousHash": "00007e8977c7a5ffc47de7f4b2951531",
		"timestamp": 1529519064246,
		"nonce": 31048,
		"hash": "0000ff35c4d2982fb578d360334d79e2"
	},
	{
		"index": 21,
		"data": [
			{
				"from": "sMJcOCBb2mfAgGHL",
				"to": "plRtv0EYjQirAoXl",
				"amount": 7409,
				"timestamp": 1529519112107,
				"hash": "07d8a7e40b7110d5531ebd7d298e4d77"
			}
		],
		"previousHash": "0000ff35c4d2982fb578d360334d79e2",
		"timestamp": 1529519112107,
		"nonce": 71617,
		"hash": "0000d18b5c3852e1573400c4f7f12a45"
	},
	{
		"index": 22,
		"data": [
			{
				"from": "eit0t9hU29cRPxN8",
				"to": "6vZwmQB0CV17DmGC",
				"amount": 4432,
				"timestamp": 1529519113109,
				"hash": "0a5d155c04f8402c311a16c819053522"
			}
		],
		"previousHash": "0000d18b5c3852e1573400c4f7f12a45",
		"timestamp": 1529519113109,
		"nonce": 21541,
		"hash": "0000e2dc469f14fd5d21a79fb629acc3"
	},
	{
		"index": 23,
		"data": [
			{
				"from": "uBtaOXkU29yNeHrl",
				"to": "bSySwqNvKPvODXvS",
				"amount": 3524,
				"timestamp": 1529519113488,
				"hash": "8c9aa203dc10718de7d882b32ba6170a"
			}
		],
		"previousHash": "0000e2dc469f14fd5d21a79fb629acc3",
		"timestamp": 1529519113488,
		"nonce": 269712,
		"hash": "0000c033ead958d324e4db1b984e6146"
	},
	{
		"index": 24,
		"data": [
			{
				"from": "JYcJ5hxkqCdWFIJQ",
				"to": "CSjfkeUFxZVqezJo",
				"amount": 222,
				"timestamp": 1529519117482,
				"hash": "b24be2fcfd9b89fb1ab70ed520540429"
			}
		],
		"previousHash": "0000c033ead958d324e4db1b984e6146",
		"timestamp": 1529519117482,
		"nonce": 52413,
		"hash": "000074f23066de5a1d815dbcc2f6066f"
	},
	{
		"index": 25,
		"data": [
			{
				"from": "qxt3AROyOpoS7FSZ",
				"to": "y9EiVWowDURUt4KU",
				"amount": 8552,
				"timestamp": 1529519118462,
				"hash": "751fd21c0fe6330638e5125bef694c14"
			}
		],
		"previousHash": "000074f23066de5a1d815dbcc2f6066f",
		"timestamp": 1529519118462,
		"nonce": 31310,
		"hash": "00003bc6a68396f066cebe3a215e9517"
	},
	{
		"index": 26,
		"data": [
			{
				"from": "Lc6p95rxzbW0qYEh",
				"to": "ZCMjBNhHEuubkFGP",
				"amount": 8651,
				"timestamp": 1529519130866,
				"hash": "82ebd23cad02751e3dc5502c6cb581a7"
			}
		],
		"previousHash": "00003bc6a68396f066cebe3a215e9517",
		"timestamp": 1529519130866,
		"nonce": 75249,
		"hash": "0000d53880167694ea326e50436b0e56"
	},
	{
		"index": 27,
		"data": [
			{
				"from": "pNWJKdSzY7Mk9oiP",
				"to": "4HgoN8ajVqg4tyX7",
				"amount": 4582,
				"timestamp": 1529519131893,
				"hash": "c074db50373bc17d6977ca61dd93e4c3"
			}
		],
		"previousHash": "0000d53880167694ea326e50436b0e56",
		"timestamp": 1529519131893,
		"nonce": 69933,
		"hash": "000021fc2c2621384063304c9c03ea14"
	},
	{
		"index": 28,
		"data": [
			{
				"from": "L6VtlXsln6hnAqKY",
				"to": "NrBP0rSj3y1tfCWE",
				"amount": 4754,
				"timestamp": 1529519133226,
				"hash": "c29494fa3b281f0d18bad4efcca4e3eb"
			}
		],
		"previousHash": "000021fc2c2621384063304c9c03ea14",
		"timestamp": 1529519133226,
		"nonce": 46832,
		"hash": "0000df948c3481585cb8c8d4809897e6"
	},
	{
		"index": 29,
		"data": [
			{
				"from": "KFSXMxb43yUYiewu",
				"to": "37CKstHC4whOjtW8",
				"amount": 9898,
				"timestamp": 1529519134196,
				"hash": "22d0e05cf3c988e20ecf39cfb313d39e"
			}
		],
		"previousHash": "0000df948c3481585cb8c8d4809897e6",
		"timestamp": 1529519134196,
		"nonce": 73425,
		"hash": "00006670c55860b0e7078f1efdec2b7c"
	},
	{
		"index": 30,
		"data": [
			{
				"from": "uOGqz4FXnI9x8HvV",
				"to": "uBA2sysDBQPPM62e",
				"amount": 1934,
				"timestamp": 1529519135864,
				"hash": "1882f73984662702258780836cae316d"
			}
		],
		"previousHash": "00006670c55860b0e7078f1efdec2b7c",
		"timestamp": 1529519135864,
		"nonce": 67071,
		"hash": "000018fd0600e43bd341e42e9680978b"
	},
	{
		"index": 31,
		"data": [
			{
				"from": "tOxq0UMyD5qdt1qn",
				"to": "dZcv4AzkLPKtJ3jN",
				"amount": 4789,
				"timestamp": 1529519136984,
				"hash": "376a2406138d5b6c1de73802ccacb6e1"
			}
		],
		"previousHash": "000018fd0600e43bd341e42e9680978b",
		"timestamp": 1529519136984,
		"nonce": 40497,
		"hash": "000024e3662a6eaad55103aeeb9ed9b9"
	},
	{
		"index": 32,
		"data": [
			{
				"from": "fES569FjqnDuhTCs",
				"to": "HpwMQkf5v1c2sSGo",
				"amount": 2545,
				"timestamp": 1529519137641,
				"hash": "96dcc5502b9667c8603dac134a2fc316"
			}
		],
		"previousHash": "000024e3662a6eaad55103aeeb9ed9b9",
		"timestamp": 1529519137641,
		"nonce": 6910,
		"hash": "0000b63613f0404ed93b534eca323319"
	},
	{
		"index": 33,
		"data": [
			{
				"from": "a6rPBud05Ol3woPI",
				"to": "SU0ifGSbmwk5JhNz",
				"amount": 6426,
				"timestamp": 1529519137820,
				"hash": "f7888d72f8f790524c781d9d7eca4757"
			}
		],
		"previousHash": "0000b63613f0404ed93b534eca323319",
		"timestamp": 1529519137820,
		"nonce": 131620,
		"hash": "000066b39ad8bd644d67180c01a6f12c"
	},
	{
		"index": 34,
		"data": [
			{
				"from": "XQ6xX4Fkx11ZcTAZ",
				"to": "FvqVyH38N9vFf520",
				"amount": 146,
				"timestamp": 1529519139829,
				"hash": "abf1fdf9238b2af94c92d65e3e469bf5"
			}
		],
		"previousHash": "000066b39ad8bd644d67180c01a6f12c",
		"timestamp": 1529519139829,
		"nonce": 51079,
		"hash": "00000425e18408e69fc28a169648933e"
	},
	{
		"index": 35,
		"data": [
			{
				"from": "knWFgswKRrnbWY41",
				"to": "56MO3yO87eOGDeCA",
				"amount": 4628,
				"timestamp": 1529519140726,
				"hash": "1fca68a6dfa578079a162e1db492e1ab"
			}
		],
		"previousHash": "00000425e18408e69fc28a169648933e",
		"timestamp": 1529519140726,
		"nonce": 105925,
		"hash": "0000a33a292bdc906da8ff747387a198"
	},
	{
		"index": 36,
		"data": [
			{
				"from": "SCHfSXCQ81oWtiR1",
				"to": "j3fVjXgKI2zEjIFO",
				"amount": 9046,
				"timestamp": 1529519142446,
				"hash": "e76ce1168831a283d1bda9fcb065c3d8"
			}
		],
		"previousHash": "0000a33a292bdc906da8ff747387a198",
		"timestamp": 1529519142446,
		"nonce": 4136,
		"hash": "000076a7f17367026972b76a4f9974ae"
	},
	{
		"index": 37,
		"data": [
			{
				"from": "dJqqIJMyXMfuRGPj",
				"to": "idP7XDky9LfTILzs",
				"amount": 432,
				"timestamp": 1529519142514,
				"hash": "e5ea97380873b0a2954efe6387e15ae7"
			}
		],
		"previousHash": "000076a7f17367026972b76a4f9974ae",
		"timestamp": 1529519142514,
		"nonce": 36855,
		"hash": "0000e62f107759ebe781098b40230514"
	},
	{
		"index": 38,
		"data": [
			{
				"from": "FOEG1TIGykrs7LAT",
				"to": "gcDtNiCL0Q6IzSWD",
				"amount": 1555,
				"timestamp": 1529519143151,
				"hash": "06a34d37fe2559f127152a9061600d58"
			}
		],
		"previousHash": "0000e62f107759ebe781098b40230514",
		"timestamp": 1529519143151,
		"nonce": 162721,
		"hash": "00007cee83dfe05d243216f811a3d1f6"
	},
	{
		"index": 39,
		"data": [
			{
				"from": "S67NongVAE5jq0c6",
				"to": "F0tKl20difELDrmn",
				"amount": 8679,
				"timestamp": 1529519145563,
				"hash": "553072ea1ab106463cd8a781e2a0dd08"
			}
		],
		"previousHash": "00007cee83dfe05d243216f811a3d1f6",
		"timestamp": 1529519145563,
		"nonce": 8919,
		"hash": "00000e6cd00aac323298e327f6e54c09"
	},
	{
		"index": 40,
		"data": [
			{
				"from": "StuZyqWTXsT1xUhU",
				"to": "bnX1cff9t7TKi5TL",
				"amount": 8144,
				"timestamp": 1529519145721,
				"hash": "20ae32b1a77da3db7a6c771915fdc6c6"
			}
		],
		"previousHash": "00000e6cd00aac323298e327f6e54c09",
		"timestamp": 1529519145721,
		"nonce": 82833,
		"hash": "0000987d460bf52566239df9fdceb593"
	},
	{
		"index": 41,
		"data": [
			{
				"from": "biewVo1bELry9vJi",
				"to": "cYPZEKeXA0QWPgow",
				"amount": 7337,
				"timestamp": 1529519147566,
				"hash": "6dd05fc124a887efc37214c026d11d21"
			}
		],
		"previousHash": "0000987d460bf52566239df9fdceb593",
		"timestamp": 1529519147566,
		"nonce": 96934,
		"hash": "000018b1669890bb7b51bad13f2657d2"
	},
	{
		"index": 42,
		"data": [
			{
				"from": "aQTnfCLvpjrL5CRE",
				"to": "ACIKJORKbHiv4uHq",
				"amount": 3259,
				"timestamp": 1529519150146,
				"hash": "32cf4e24ec6b1a27c3177f3bba0fb6ee"
			}
		],
		"previousHash": "000018b1669890bb7b51bad13f2657d2",
		"timestamp": 1529519150147,
		"nonce": 101588,
		"hash": "000086e873ca8a3db57b4fdeffeacaef"
	},
	{
		"index": 43,
		"data": [
			{
				"from": "3JcYCWT4bOfGEhAZ",
				"to": "90VOyBnbvTsWywDW",
				"amount": 953,
				"timestamp": 1529519152106,
				"hash": "ffc0e95e385046fb0e929a8f60c630e4"
			}
		],
		"previousHash": "000086e873ca8a3db57b4fdeffeacaef",
		"timestamp": 1529519152107,
		"nonce": 75208,
		"hash": "0000528cb11424297e2f8e983e34a003"
	},
	{
		"index": 44,
		"data": [
			{
				"from": "XOHaYhLv0HWIzqBl",
				"to": "qOQIxPLxa6yY8YXP",
				"amount": 7486,
				"timestamp": 1529519153634,
				"hash": "789cee6ca06b371b2d097f8d1d7f9d33"
			}
		],
		"previousHash": "0000528cb11424297e2f8e983e34a003",
		"timestamp": 1529519153634,
		"nonce": 7375,
		"hash": "0000de7d705f389e71be9203732381dc"
	},
	{
		"index": 45,
		"data": [
			{
				"from": "LJiCCSDa2FuLn1Rr",
				"to": "HLnVXCiMEjyBE2bP",
				"amount": 1809,
				"timestamp": 1529519153798,
				"hash": "4e2a872aa88961989ef20c4cbc92ee0a"
			}
		],
		"previousHash": "0000de7d705f389e71be9203732381dc",
		"timestamp": 1529519153798,
		"nonce": 7764,
		"hash": "0000f4baf4d60b24844d30adef9826ab"
	},
	{
		"index": 46,
		"data": [
			{
				"from": "2PVM7cv2Vj4xr1Dk",
				"to": "R4daWeVDrssLc2Ee",
				"amount": 2727,
				"timestamp": 1529519153977,
				"hash": "c6200620043362db94f7ca7d8b20b472"
			}
		],
		"previousHash": "0000f4baf4d60b24844d30adef9826ab",
		"timestamp": 1529519153977,
		"nonce": 77952,
		"hash": "0000cbd7963583e41f2bbb5c0a579837"
	},
	{
		"index": 47,
		"data": [
			{
				"from": "G22hcH0FTNcYfdJL",
				"to": "j8hoWHQstzYHzAd1",
				"amount": 8789,
				"timestamp": 1529519155526,
				"hash": "3ec914ab15af272afd5d6e296af631a8"
			}
		],
		"previousHash": "0000cbd7963583e41f2bbb5c0a579837",
		"timestamp": 1529519155526,
		"nonce": 649,
		"hash": "0000f2e9ae0acded96a52e616a8c39e4"
	},
	{
		"index": 48,
		"data": [
			{
				"from": "y60rTRMZ333MaAaz",
				"to": "FQa33nJDdD34o5Xd",
				"amount": 9366,
				"timestamp": 1529519155545,
				"hash": "8ecd989ef2d7a0c55ddaa6adb77ebe69"
			}
		],
		"previousHash": "0000f2e9ae0acded96a52e616a8c39e4",
		"timestamp": 1529519155545,
		"nonce": 163929,
		"hash": "0000df3cf7cad5a928f34c67fa3510b6"
	},
	{
		"index": 49,
		"data": [
			{
				"from": "7Jg9ybsiMoZPy42G",
				"to": "YCvsJuI25Y3sh9Nx",
				"amount": 4062,
				"timestamp": 1529519158549,
				"hash": "fa1c73681397dbd8023cf08638614032"
			}
		],
		"previousHash": "0000df3cf7cad5a928f34c67fa3510b6",
		"timestamp": 1529519158549,
		"nonce": 107945,
		"hash": "0000932b9b5dede85957a296dd9e83df"
	},
	{
		"index": 50,
		"data": [
			{
				"from": "frjYKpRyPP4PLv6J",
				"to": "SJGTgCqNUTHhUIbx",
				"amount": 993,
				"timestamp": 1529519160838,
				"hash": "120d864c9f6beb24995feacaa1ce5bfb"
			}
		],
		"previousHash": "0000932b9b5dede85957a296dd9e83df",
		"timestamp": 1529519160838,
		"nonce": 43278,
		"hash": "0000d86097999aae4fff3f817c945afa"
	},
	{
		"index": 51,
		"data": [
			{
				"from": "DqEilkFxS0oZtb9c",
				"to": "NSeh1afohNKTcnX0",
				"amount": 271,
				"timestamp": 1529519209082,
				"hash": "3cf23fe4d6ad5c665addc3847a4a4c14"
			}
		],
		"previousHash": "0000d86097999aae4fff3f817c945afa",
		"timestamp": 1529519209082,
		"nonce": 1257,
		"hash": "0000c149c2b1728a3309f8ef23c511fb"
	},
	{
		"index": 52,
		"data": [
			{
				"from": "xvjNSo9tpQtsnfZF",
				"to": "ZCiGtVncq0NlQnyX",
				"amount": 1295,
				"timestamp": 1529519209114,
				"hash": "034498a4dda6832d076448f0dbb6abc8"
			}
		],
		"previousHash": "0000c149c2b1728a3309f8ef23c511fb",
		"timestamp": 1529519209114,
		"nonce": 253827,
		"hash": "00000ad674753705485d7f4000230a44"
	},
	{
		"index": 53,
		"data": [
			{
				"from": "qOaNkKy4C0gQ6AJX",
				"to": "dBxTzKgPvCj43swe",
				"amount": 291,
				"timestamp": 1529519212994,
				"hash": "78a68fa47ec992e2c71d1c085d6a1513"
			}
		],
		"previousHash": "00000ad674753705485d7f4000230a44",
		"timestamp": 1529519212994,
		"nonce": 52511,
		"hash": "000057b329b28b6f8a278ad207011673"
	},
	{
		"index": 54,
		"data": [
			{
				"from": "4OmNSgq3ENW65GND",
				"to": "lcCka8qDGtzXu0BH",
				"amount": 2696,
				"timestamp": 1529519213985,
				"hash": "bc8581d87c16416535e844fab29bc496"
			}
		],
		"previousHash": "000057b329b28b6f8a278ad207011673",
		"timestamp": 1529519213985,
		"nonce": 86297,
		"hash": "000025b904fb6284980f6f65899e3936"
	},
	{
		"index": 55,
		"data": [
			{
				"from": "uxpZD72bYzr0YoER",
				"to": "4Pt6d3FPwYzjcJro",
				"amount": 1145,
				"timestamp": 1529519215514,
				"hash": "de0e57a9a3f457afd8f72a9f36eeb396"
			}
		],
		"previousHash": "000025b904fb6284980f6f65899e3936",
		"timestamp": 1529519215514,
		"nonce": 29599,
		"hash": "00008255e76635729f42fb19f045dceb"
	},
	{
		"index": 56,
		"data": [
			{
				"from": "dMkKlvuwZFiCekjh",
				"to": "YbJNJiSxv9iFfJUQ",
				"amount": 4946,
				"timestamp": 1529519216062,
				"hash": "82c83b2cb29032aa992c82eeca3e8b84"
			}
		],
		"previousHash": "00008255e76635729f42fb19f045dceb",
		"timestamp": 1529519216062,
		"nonce": 112970,
		"hash": "0000906a40119ef650f73abac723ff09"
	},
	{
		"index": 57,
		"data": [
			{
				"from": "nVwkQtdW0LBCVCmM",
				"to": "Cph6H6jQ5IyLzZ8f",
				"amount": 4080,
				"timestamp": 1529519218126,
				"hash": "4b795beba79445dd115c7d431099cf5b"
			}
		],
		"previousHash": "0000906a40119ef650f73abac723ff09",
		"timestamp": 1529519218126,
		"nonce": 54586,
		"hash": "000042966f28241ae832e9878df6bbbf"
	},
	{
		"index": 58,
		"data": [
			{
				"from": "i5gwuqdMQtxC82dk",
				"to": "l6bqf4B36iAY8kvW",
				"amount": 4476,
				"timestamp": 1529519219283,
				"hash": "e219b7c725add377550de88c03e7c859"
			}
		],
		"previousHash": "000042966f28241ae832e9878df6bbbf",
		"timestamp": 1529519219283,
		"nonce": 26032,
		"hash": "0000060c02177ed8b276e81f6ad09fe4"
	},
	{
		"index": 59,
		"data": [
			{
				"from": "x0hu8mdNrgYQS5yi",
				"to": "IMTOxgrmZQK83VTl",
				"amount": 5283,
				"timestamp": 1529519220000,
				"hash": "606f7ce66da63f8326d4f7c82f6cb6c3"
			}
		],
		"previousHash": "0000060c02177ed8b276e81f6ad09fe4",
		"timestamp": 1529519220000,
		"nonce": 56008,
		"hash": "000090ef2f402ae433d60afabc7e8fa5"
	},
	{
		"index": 60,
		"data": [
			{
				"from": "oEYwjJ2tUjjGTcxG",
				"to": "LBHh1maRYtFMrx4J",
				"amount": 4844,
				"timestamp": 1529519221083,
				"hash": "219974a16218a68e09b7b209bce53a97"
			}
		],
		"previousHash": "000090ef2f402ae433d60afabc7e8fa5",
		"timestamp": 1529519221083,
		"nonce": 35697,
		"hash": "000034546d4c941cee99474cd0e7bd26"
	},
	{
		"index": 61,
		"data": [
			{
				"from": "67VflcdVmIyMcto3",
				"to": "KRlodASXg8pWW744",
				"amount": 8658,
				"timestamp": 1529519221785,
				"hash": "43974349de42eeb5a0e5ce0f5c22a7aa"
			}
		],
		"previousHash": "000034546d4c941cee99474cd0e7bd26",
		"timestamp": 1529519221785,
		"nonce": 270976,
		"hash": "0000d8e90a2b56e434ff94c3b443edf1"
	},
	{
		"index": 62,
		"data": [
			{
				"from": "s4OlinSv4Y4Purdz",
				"to": "TPf9dlgWWEPMcVWN",
				"amount": 2283,
				"timestamp": 1529519226762,
				"hash": "15e4db6fb0e87c35f0af1affaa08c1a1"
			}
		],
		"previousHash": "0000d8e90a2b56e434ff94c3b443edf1",
		"timestamp": 1529519226762,
		"nonce": 33793,
		"hash": "0000e5cc1844258ee8c1617860546b97"
	},
	{
		"index": 63,
		"data": [
			{
				"from": "lXaucBUuJamvYeBI",
				"to": "pjAGKDga9y1osIv6",
				"amount": 6981,
				"timestamp": 1529519227729,
				"hash": "f308be1cb021cc23f2f4d5b9d7d8edfb"
			}
		],
		"previousHash": "0000e5cc1844258ee8c1617860546b97",
		"timestamp": 1529519227729,
		"nonce": 48754,
		"hash": "0000df37915b862f91743c0689149676"
	},
	{
		"index": 64,
		"data": [
			{
				"from": "EDOQJ4Bv0iIPm6Js",
				"to": "ucZxWauFAE3wYnO1",
				"amount": 4911,
				"timestamp": 1529519228849,
				"hash": "ec60b075c34e060795da39f8008ea62a"
			}
		],
		"previousHash": "0000df37915b862f91743c0689149676",
		"timestamp": 1529519228850,
		"nonce": 215827,
		"hash": "0000ed7b7eb2df0c4ab6bc95975179b3"
	},
	{
		"index": 65,
		"data": [
			{
				"from": "1MdRoSE3EIen7hmT",
				"to": "vNhJFBNO0hC8etun",
				"amount": 2983,
				"timestamp": 1529519234012,
				"hash": "23e4c75d8b22e65ac825f437fec1878e"
			}
		],
		"previousHash": "0000ed7b7eb2df0c4ab6bc95975179b3",
		"timestamp": 1529519234012,
		"nonce": 145370,
		"hash": "0000a372885f8d7c51c1072291f3ce28"
	},
	{
		"index": 66,
		"data": [
			{
				"from": "KSVXCpqUGtj0MX8c",
				"to": "ObqkyJl1J1MG1AWl",
				"amount": 8211,
				"timestamp": 1529519237025,
				"hash": "ed41f26bcde8946a43320c8e603420fd"
			}
		],
		"previousHash": "0000a372885f8d7c51c1072291f3ce28",
		"timestamp": 1529519237025,
		"nonce": 2243,
		"hash": "0000cd1b9c4ba9cd4b9164138358b3b4"
	},
	{
		"index": 67,
		"data": [
			{
				"from": "IgAMeOZMF6WOgawk",
				"to": "sfZ9xlFgiFvH7vZM",
				"amount": 3417,
				"timestamp": 1529519237077,
				"hash": "c028ee347da9048bf6b3c8b1a2fc7682"
			}
		],
		"previousHash": "0000cd1b9c4ba9cd4b9164138358b3b4",
		"timestamp": 1529519237077,
		"nonce": 13910,
		"hash": "0000a2912092c0c51494a43bc98efe34"
	},
	{
		"index": 68,
		"data": [
			{
				"from": "ewWfTTrrADl8X5m7",
				"to": "VqdQqP9Jsb8ZeuQo",
				"amount": 6349,
				"timestamp": 1529519237357,
				"hash": "c72767f6b79feb551fd40d64ee0f7ae6"
			}
		],
		"previousHash": "0000a2912092c0c51494a43bc98efe34",
		"timestamp": 1529519237357,
		"nonce": 53564,
		"hash": "0000676890657affc31e67fa0c123b7d"
	},
	{
		"index": 69,
		"data": [
			{
				"from": "RE2J1EoOQskdmXmE",
				"to": "cI6LW9UfcrBSACah",
				"amount": 1102,
				"timestamp": 1529519238429,
				"hash": "163591349b27d9b78de6a63aa0277903"
			}
		],
		"previousHash": "0000676890657affc31e67fa0c123b7d",
		"timestamp": 1529519238429,
		"nonce": 14395,
		"hash": "00001f162e3667768d747df0f4b97fab"
	},
	{
		"index": 70,
		"data": [
			{
				"from": "B14DBd0qLfuWMJYX",
				"to": "NC1D7eCixlifYzWR",
				"amount": 5864,
				"timestamp": 1529519238759,
				"hash": "a8066c99d11eacfce05448fd95f3c924"
			}
		],
		"previousHash": "00001f162e3667768d747df0f4b97fab",
		"timestamp": 1529519238759,
		"nonce": 9043,
		"hash": "00005066754a01dce03849451b28d125"
	},
	{
		"index": 71,
		"data": [
			{
				"from": "cYfj2eQevYWlL6Du",
				"to": "GlNuXfvR943RKCRC",
				"amount": 1292,
				"timestamp": 1529519238965,
				"hash": "ca5835f4e7ceeb065c227ecd10c422d0"
			}
		],
		"previousHash": "00005066754a01dce03849451b28d125",
		"timestamp": 1529519238966,
		"nonce": 21071,
		"hash": "000072380ea0cf791636c6759a566e06"
	},
	{
		"index": 72,
		"data": [
			{
				"from": "96qqDg1WCDuW8Vod",
				"to": "1MvWaCJ56la6yxhu",
				"amount": 3963,
				"timestamp": 1529519239373,
				"hash": "1dfde728218d4e957fd3ab5aa488053d"
			}
		],
		"previousHash": "000072380ea0cf791636c6759a566e06",
		"timestamp": 1529519239373,
		"nonce": 30952,
		"hash": "00000aa29800c597b9882fa579b44cdd"
	},
	{
		"index": 73,
		"data": [
			{
				"from": "MfuLVjv7Kvh4qxlA",
				"to": "QK2e5hX0kxEIpKwR",
				"amount": 5733,
				"timestamp": 1529519240159,
				"hash": "9682f21343a813de7ae70c4cc1ef1661"
			}
		],
		"previousHash": "00000aa29800c597b9882fa579b44cdd",
		"timestamp": 1529519240159,
		"nonce": 33093,
		"hash": "0000b7cbd799da51b217e9dc05e8ee68"
	},
	{
		"index": 74,
		"data": [
			{
				"from": "zbOzmxqpn5ECAt0Y",
				"to": "2lQkioTICCiIZmGE",
				"amount": 7953,
				"timestamp": 1529519240919,
				"hash": "10830fb9f95caf443eac039740873dba"
			}
		],
		"previousHash": "0000b7cbd799da51b217e9dc05e8ee68",
		"timestamp": 1529519240919,
		"nonce": 23187,
		"hash": "0000bd1d6def8d3133e4d150d90c07d9"
	},
	{
		"index": 75,
		"data": [
			{
				"from": "Uuy5S6xsCtPzUOcC",
				"to": "tZJ1PoXftTMHiCPQ",
				"amount": 6179,
				"timestamp": 1529519241337,
				"hash": "e874e20619883191dbe87013f208787c"
			}
		],
		"previousHash": "0000bd1d6def8d3133e4d150d90c07d9",
		"timestamp": 1529519241337,
		"nonce": 261409,
		"hash": "0000715a70512dea0ecc93ab3896d98c"
	},
	{
		"index": 76,
		"data": [
			{
				"from": "tIjSHMqDFLzn935j",
				"to": "BczkqoutSxmKzrYB",
				"amount": 3485,
				"timestamp": 1529519245904,
				"hash": "f912a0f5e5e0c32452cc8e10eb30d3c8"
			}
		],
		"previousHash": "0000715a70512dea0ecc93ab3896d98c",
		"timestamp": 1529519245904,
		"nonce": 182469,
		"hash": "00001b417d7d406b1363a6f6405c1ffc"
	},
	{
		"index": 77,
		"data": [
			{
				"from": "gHbhlcyAXm57XTBE",
				"to": "vPpDV2XYAxzHXRAq",
				"amount": 2563,
				"timestamp": 1529519249041,
				"hash": "0aad97d8a3a7d9e0b8f2b80010729d37"
			}
		],
		"previousHash": "00001b417d7d406b1363a6f6405c1ffc",
		"timestamp": 1529519249042,
		"nonce": 65797,
		"hash": "00000b3c5a0a8d9558782eea19cfb382"
	},
	{
		"index": 78,
		"data": [
			{
				"from": "Eo9QTFoqoSYS3qpI",
				"to": "FD2Lr6MZTv4ALFvO",
				"amount": 8397,
				"timestamp": 1529519250360,
				"hash": "c254fb53c425de88869762b418955764"
			}
		],
		"previousHash": "00000b3c5a0a8d9558782eea19cfb382",
		"timestamp": 1529519250361,
		"nonce": 109719,
		"hash": "00006fbe7e24c4a2f5ea324047049210"
	},
	{
		"index": 79,
		"data": [
			{
				"from": "2pM6hAtRJHh2hoMS",
				"to": "7cmavFzqs4zL70Wv",
				"amount": 4490,
				"timestamp": 1529519252392,
				"hash": "999e200adbf2b4b6535a5dab47ecba54"
			}
		],
		"previousHash": "00006fbe7e24c4a2f5ea324047049210",
		"timestamp": 1529519252392,
		"nonce": 105244,
		"hash": "0000dee2e986f03bf2a7ef35daf89289"
	},
	{
		"index": 80,
		"data": [
			{
				"from": "xZVEitONOzQV829v",
				"to": "FSGoyVl9ZW8QByph",
				"amount": 431,
				"timestamp": 1529519254267,
				"hash": "8e841e33388aec75065c9f7aae3a0c6d"
			}
		],
		"previousHash": "0000dee2e986f03bf2a7ef35daf89289",
		"timestamp": 1529519254267,
		"nonce": 54895,
		"hash": "00003b13b5beb5362da062c4496088bd"
	},
	{
		"index": 81,
		"data": [
			{
				"from": "IEcT6QxR3zfQ4sOk",
				"to": "bFzoaLxx7KJbhqFT",
				"amount": 7235,
				"timestamp": 1529519255611,
				"hash": "f193c671ec117ccd532440705ac9e0d0"
			}
		],
		"previousHash": "00003b13b5beb5362da062c4496088bd",
		"timestamp": 1529519255611,
		"nonce": 77424,
		"hash": "00008b6cc39c3cabe5e56487a70138ae"
	},
	{
		"index": 82,
		"data": [
			{
				"from": "NJF8J9mNfnhKy0in",
				"to": "JMvOGnBlISDC71qo",
				"amount": 1609,
				"timestamp": 1529519257182,
				"hash": "34ecb562a9a46b020f7d1b5cd5b810ff"
			}
		],
		"previousHash": "00008b6cc39c3cabe5e56487a70138ae",
		"timestamp": 1529519257183,
		"nonce": 65540,
		"hash": "000062373abdf245e7e3dcecad541e97"
	},
	{
		"index": 83,
		"data": [
			{
				"from": "ql3MdXj79LXoUzvn",
				"to": "bDWDjmf51I7yNrKL",
				"amount": 1637,
				"timestamp": 1529519258404,
				"hash": "6b56553b75d5362fe3208f40ec96a3fa"
			}
		],
		"previousHash": "000062373abdf245e7e3dcecad541e97",
		"timestamp": 1529519258404,
		"nonce": 96199,
		"hash": "0000e3435178fcf5b4e93e01ee8bc98e"
	},
	{
		"index": 84,
		"data": [
			{
				"from": "oghvyEhqTqazOmX4",
				"to": "1dGKhiAQYcQtaGGx",
				"amount": 1708,
				"timestamp": 1529519260323,
				"hash": "9638dd65f0a362d4a1f2118e0d70efe6"
			}
		],
		"previousHash": "0000e3435178fcf5b4e93e01ee8bc98e",
		"timestamp": 1529519260323,
		"nonce": 30075,
		"hash": "0000ad85d343142ba29354d2d70aea2f"
	},
	{
		"index": 85,
		"data": [
			{
				"from": "dczA4fdpOjbmY5Hy",
				"to": "DjajdnI60cfhDGvB",
				"amount": 6630,
				"timestamp": 1529519260949,
				"hash": "0d2904eced021e5bcf6a2ffaf7d023bd"
			}
		],
		"previousHash": "0000ad85d343142ba29354d2d70aea2f",
		"timestamp": 1529519260949,
		"nonce": 44065,
		"hash": "00009e08354ef18ccda4cd7d36a4dba0"
	},
	{
		"index": 86,
		"data": [
			{
				"from": "IZyzUPGPYTYtpo1U",
				"to": "2funLgEe6DZKxFE8",
				"amount": 3363,
				"timestamp": 1529519261906,
				"hash": "3a763381c691d99d836f9d8a46c70216"
			}
		],
		"previousHash": "00009e08354ef18ccda4cd7d36a4dba0",
		"timestamp": 1529519261906,
		"nonce": 95650,
		"hash": "00008b72937571f30fb2095bfafee5c7"
	},
	{
		"index": 87,
		"data": [
			{
				"from": "FSy1VGwY7e2dmfSe",
				"to": "p0LQAd4unFiLP3mc",
				"amount": 1637,
				"timestamp": 1529519264020,
				"hash": "fbb97e936a7f02fa5a7f43d1278e2b58"
			}
		],
		"previousHash": "00008b72937571f30fb2095bfafee5c7",
		"timestamp": 1529519264020,
		"nonce": 7293,
		"hash": "00009160c61dab0d1edb67d3287a6a4b"
	},
	{
		"index": 88,
		"data": [
			{
				"from": "9smcs2JF28mNSEvd",
				"to": "gH1LCJ7DVcbKptaB",
				"amount": 6426,
				"timestamp": 1529519264157,
				"hash": "74c35b85510fbc4923553b33b28340c2"
			}
		],
		"previousHash": "00009160c61dab0d1edb67d3287a6a4b",
		"timestamp": 1529519264157,
		"nonce": 88504,
		"hash": "00002516d4a291cc7d2d72ca1a2565ad"
	},
	{
		"index": 89,
		"data": [
			{
				"from": "9x8r351kHYBqEzZq",
				"to": "Uu7O7rXM9D7nnHGz",
				"amount": 7105,
				"timestamp": 1529519266275,
				"hash": "b5e72684b7c7110cadfba3a60ddd32fe"
			}
		],
		"previousHash": "00002516d4a291cc7d2d72ca1a2565ad",
		"timestamp": 1529519266275,
		"nonce": 116550,
		"hash": "0000193731292c8937279234b32ea8e3"
	},
	{
		"index": 90,
		"data": [
			{
				"from": "fap54Np4bMRiT5xP",
				"to": "VCQYU8ybzeHzVqQz",
				"amount": 4860,
				"timestamp": 1529519268829,
				"hash": "90f6ba87ec150b4c88c2a859bba6cbbf"
			}
		],
		"previousHash": "0000193731292c8937279234b32ea8e3",
		"timestamp": 1529519268829,
		"nonce": 5007,
		"hash": "00001b288a6a321be56eba1145894b11"
	},
	{
		"index": 91,
		"data": [
			{
				"from": "Ue5JeXVRv968fiIn",
				"to": "iJ0Ri8LcBZI51Vll",
				"amount": 5799,
				"timestamp": 1529519268940,
				"hash": "b1c8aaec2b259efeb1eef98cbc44b3b8"
			}
		],
		"previousHash": "00001b288a6a321be56eba1145894b11",
		"timestamp": 1529519268940,
		"nonce": 129502,
		"hash": "0000c59caa0a1cae963dc99c670749c7"
	},
	{
		"index": 92,
		"data": [
			{
				"from": "jHKruXhHGSgtkU2H",
				"to": "GMWL7TpBDQsij1lp",
				"amount": 6729,
				"timestamp": 1529519271555,
				"hash": "132ac17b8a9b793930164c94b8d71c72"
			}
		],
		"previousHash": "0000c59caa0a1cae963dc99c670749c7",
		"timestamp": 1529519271555,
		"nonce": 119712,
		"hash": "0000196bbdd392f7d97c01be68452045"
	},
	{
		"index": 93,
		"data": [
			{
				"from": "gaJF5fB2de2MFvg1",
				"to": "sshJcmw2n441wZdl",
				"amount": 6810,
				"timestamp": 1529519274331,
				"hash": "145d5d2cefbaa2401e8b49c5bb250988"
			}
		],
		"previousHash": "0000196bbdd392f7d97c01be68452045",
		"timestamp": 1529519274331,
		"nonce": 166987,
		"hash": "0000aa52610c6959db2e63e49290b500"
	},
	{
		"index": 94,
		"data": [
			{
				"from": "7iBLaRIif1TtXnhT",
				"to": "Xo4qQvHNIQaocye1",
				"amount": 2005,
				"timestamp": 1529519277863,
				"hash": "366dda4774e6a95203eb7d43cb25624b"
			}
		],
		"previousHash": "0000aa52610c6959db2e63e49290b500",
		"timestamp": 1529519277863,
		"nonce": 299,
		"hash": "00008e9d23d0d29b277f90c2f81cc5ff"
	},
	{
		"index": 95,
		"data": [
			{
				"from": "EEgVkGLgu2hjZg2T",
				"to": "BNbPTzsV24J2quEW",
				"amount": 6642,
				"timestamp": 1529519277894,
				"hash": "f5f0bab2f40a4fb4368a5b649aeaf968"
			}
		],
		"previousHash": "00008e9d23d0d29b277f90c2f81cc5ff",
		"timestamp": 1529519277894,
		"nonce": 4395,
		"hash": "000093983917d68c7798ed833bc3125a"
	},
	{
		"index": 96,
		"data": [
			{
				"from": "BI7yZK7xKfGLZjK1",
				"to": "4BW1iynoVrhrr1yp",
				"amount": 2598,
				"timestamp": 1529519278028,
				"hash": "92c953a19628b57229171a8eaed75a89"
			}
		],
		"previousHash": "000093983917d68c7798ed833bc3125a",
		"timestamp": 1529519278029,
		"nonce": 16879,
		"hash": "0000f15d9748a950cfef09f809870fc7"
	},
	{
		"index": 97,
		"data": [
			{
				"from": "M7628i10NH8WXFpZ",
				"to": "2ayrr6xOpYnKrqRc",
				"amount": 1757,
				"timestamp": 1529519278444,
				"hash": "ec59a1d1cf96101d6de70f2c2b117522"
			}
		],
		"previousHash": "0000f15d9748a950cfef09f809870fc7",
		"timestamp": 1529519278445,
		"nonce": 3254,
		"hash": "000017e72146a30e5fffbc9fbe174c9f"
	},
	{
		"index": 98,
		"data": [
			{
				"from": "2ixzGrFVCSrcjOOy",
				"to": "CM5k7C9DmC30cgtd",
				"amount": 6701,
				"timestamp": 1529519278549,
				"hash": "e355744d9bdff5638e147c8123b28665"
			}
		],
		"previousHash": "000017e72146a30e5fffbc9fbe174c9f",
		"timestamp": 1529519278549,
		"nonce": 88900,
		"hash": "0000ca2b2d268581ffa022dbab37139d"
	},
	{
		"index": 99,
		"data": [
			{
				"from": "JlYNcSioZwxj6cZ3",
				"to": "ykeWNiO37HApDpyx",
				"amount": 1994,
				"timestamp": 1529519280283,
				"hash": "9ea5850851bf5c7d2d98d1170ee2d346"
			}
		],
		"previousHash": "0000ca2b2d268581ffa022dbab37139d",
		"timestamp": 1529519280284,
		"nonce": 246563,
		"hash": "00007c168602b18bce0fa573cf2c12f0"
	},
	{
		"index": 100,
		"data": [
			{
				"from": "MEgmPuT9jsavYIau",
				"to": "PKf5tldELMJUnvPj",
				"amount": 4165,
				"timestamp": 1529519285553,
				"hash": "9e91064ac302a136672d289ea51801e5"
			}
		],
		"previousHash": "00007c168602b18bce0fa573cf2c12f0",
		"timestamp": 1529519285553,
		"nonce": 6674,
		"hash": "000075395a5ff5c444fe2bf103cff960"
	},
	{
		"index": 101,
		"data": [
			{
				"from": "G7LC6ywjqxzzY97z",
				"to": "1nF6sQmKpuAQjzUO",
				"amount": 1054,
				"timestamp": 1529519342723,
				"hash": "125b2132066ea060f63a7adbc2bc09a0"
			}
		],
		"previousHash": "000075395a5ff5c444fe2bf103cff960",
		"timestamp": 1529519342723,
		"nonce": 126613,
		"hash": "0000910c69303d967ec0a0bce0eaac91"
	},
	{
		"index": 102,
		"data": [
			{
				"from": "cXQqKjMC60yYTOwH",
				"to": "szp0uGudkhEE3bud",
				"amount": 9134,
				"timestamp": 1529519344481,
				"hash": "2623330d069a80cf4fc24d62a29927c6"
			}
		],
		"previousHash": "0000910c69303d967ec0a0bce0eaac91",
		"timestamp": 1529519344481,
		"nonce": 8265,
		"hash": "00007979cbed9e67b94764354c025fbf"
	},
	{
		"index": 103,
		"data": [
			{
				"from": "uhdNNOFvCCuxp7wo",
				"to": "EmpG2klUhYLJQFnh",
				"amount": 2786,
				"timestamp": 1529519344659,
				"hash": "b2e2c7b1a92b72b0b26d6430a4367c5d"
			}
		],
		"previousHash": "00007979cbed9e67b94764354c025fbf",
		"timestamp": 1529519344659,
		"nonce": 311696,
		"hash": "0000947bb3f80c73fb8efa6436085913"
	},
	{
		"index": 104,
		"data": [
			{
				"from": "i3gW00drYObjfkiT",
				"to": "5vk6ha6E3bLXVR7l",
				"amount": 4124,
				"timestamp": 1529519350103,
				"hash": "49b1bb7cf99d7c98056294048628950a"
			}
		],
		"previousHash": "0000947bb3f80c73fb8efa6436085913",
		"timestamp": 1529519350103,
		"nonce": 97153,
		"hash": "0000b4c4d9b5d0237fbe283d53bac122"
	},
	{
		"index": 105,
		"data": [
			{
				"from": "Rslk0IL05a2ltOyw",
				"to": "aOAphfJUhlN3fhb5",
				"amount": 3420,
				"timestamp": 1529519352003,
				"hash": "be206f28f1a74a2aa58d63390c84f077"
			}
		],
		"previousHash": "0000b4c4d9b5d0237fbe283d53bac122",
		"timestamp": 1529519352003,
		"nonce": 258309,
		"hash": "0000a10887802a4b2f059c05c53474d2"
	},
	{
		"index": 106,
		"data": [
			{
				"from": "BzX8vUr2w4kbgnzr",
				"to": "uZycQFtMldOMqCIm",
				"amount": 5810,
				"timestamp": 1529519358172,
				"hash": "2e5a4039e29b0051c8022842d6142525"
			}
		],
		"previousHash": "0000a10887802a4b2f059c05c53474d2",
		"timestamp": 1529519358172,
		"nonce": 101391,
		"hash": "0000b3e473da8f05a81589c44458ed38"
	},
	{
		"index": 107,
		"data": [
			{
				"from": "cUw2s9h1QROkgLYe",
				"to": "HX1gXLsZX5Emr1DM",
				"amount": 2747,
				"timestamp": 1529519359898,
				"hash": "b0bb32eff0593601c5ad8480e3cb7b0f"
			}
		],
		"previousHash": "0000b3e473da8f05a81589c44458ed38",
		"timestamp": 1529519359898,
		"nonce": 3053,
		"hash": "0000c2e5a8c4d67d43c560b7b024f1dd"
	},
	{
		"index": 108,
		"data": [
			{
				"from": "5seZc342BhdG24GF",
				"to": "uNCqFKeYUhzhDXya",
				"amount": 4129,
				"timestamp": 1529519359954,
				"hash": "5a22d2e16294b6e0fc2f4a9cd87f802e"
			}
		],
		"previousHash": "0000c2e5a8c4d67d43c560b7b024f1dd",
		"timestamp": 1529519359955,
		"nonce": 17071,
		"hash": "0000cb40dcd09002c30a068742121b11"
	},
	{
		"index": 109,
		"data": [
			{
				"from": "cy5CZ7bMNpaG0iSW",
				"to": "7LHgy89cTUAN9Oa2",
				"amount": 7070,
				"timestamp": 1529519360384,
				"hash": "269e343fef115a1dcee4bdedd499211b"
			}
		],
		"previousHash": "0000cb40dcd09002c30a068742121b11",
		"timestamp": 1529519360384,
		"nonce": 53428,
		"hash": "00004f8566ac784c75bf50e06b7058ac"
	},
	{
		"index": 110,
		"data": [
			{
				"from": "GGD9FGpEIMaTBROS",
				"to": "BH45KJ2FsgT1Nkpk",
				"amount": 3628,
				"timestamp": 1529519362146,
				"hash": "9021107dbaddccbe6bdc9e55edf52f17"
			}
		],
		"previousHash": "00004f8566ac784c75bf50e06b7058ac",
		"timestamp": 1529519362146,
		"nonce": 52488,
		"hash": "000003e66ee2a5741d92545d7ddaf456"
	},
	{
		"index": 111,
		"data": [
			{
				"from": "tfqCKysm5JRyiU09",
				"to": "VdKTjrGqVbWl00l0",
				"amount": 4121,
				"timestamp": 1529519364034,
				"hash": "cc4d8bea4cb87d786eb0505719e44c9f"
			}
		],
		"previousHash": "000003e66ee2a5741d92545d7ddaf456",
		"timestamp": 1529519364034,
		"nonce": 60777,
		"hash": "0000f10733568bb3df239faf36678609"
	},
	{
		"index": 112,
		"data": [
			{
				"from": "enTBg3j6w1GzuK92",
				"to": "QWKlvR9Pr3UiGMCI",
				"amount": 5709,
				"timestamp": 1529519365569,
				"hash": "d761e1f931ecf77e207eb4f345b8c8e0"
			}
		],
		"previousHash": "0000f10733568bb3df239faf36678609",
		"timestamp": 1529519365569,
		"nonce": 106880,
		"hash": "00000fd22358d375b005e42cd3bbc5df"
	},
	{
		"index": 113,
		"data": [
			{
				"from": "5dHFuc6GC5wCcnzW",
				"to": "OAlUnfMp88pgIw2g",
				"amount": 8153,
				"timestamp": 1529519367685,
				"hash": "d7ca23080ac17b7da5afb66aa3fee3cc"
			}
		],
		"previousHash": "00000fd22358d375b005e42cd3bbc5df",
		"timestamp": 1529519367685,
		"nonce": 31247,
		"hash": "00008ff042f52cb1af3d64ff0e1169e1"
	},
	{
		"index": 114,
		"data": [
			{
				"from": "WF9QFkg2Y51f3XTm",
				"to": "i702Nosp7vzzFej4",
				"amount": 8362,
				"timestamp": 1529519368415,
				"hash": "faf1bc5f985f2f6ffb2e686d9834cd8f"
			}
		],
		"previousHash": "00008ff042f52cb1af3d64ff0e1169e1",
		"timestamp": 1529519368415,
		"nonce": 37400,
		"hash": "000030aeb3fed3f9301176b7427b6446"
	},
	{
		"index": 115,
		"data": [
			{
				"from": "Ph1gdExLisBpy4rH",
				"to": "kEWIuL5ZPYkJ0BzN",
				"amount": 23,
				"timestamp": 1529519369173,
				"hash": "8d5138158bbed8bb7bb6de3ec0034453"
			}
		],
		"previousHash": "000030aeb3fed3f9301176b7427b6446",
		"timestamp": 1529519369173,
		"nonce": 16566,
		"hash": "0000c82aaa7fa860f994abb92043a375"
	},
	{
		"index": 116,
		"data": [
			{
				"from": "o8RSdCxHIZ65C7ik",
				"to": "jU2FKiS8W6uSlB6K",
				"amount": 9235,
				"timestamp": 1529519369499,
				"hash": "19f69b70cf44d750c905a263fc989731"
			}
		],
		"previousHash": "0000c82aaa7fa860f994abb92043a375",
		"timestamp": 1529519369499,
		"nonce": 85002,
		"hash": "0000183747554738bb613896b163f8b0"
	},
	{
		"index": 117,
		"data": [
			{
				"from": "CHP4gb9DhX9Jo1WL",
				"to": "ywjgI1gSt1gtUUcV",
				"amount": 9239,
				"timestamp": 1529519371218,
				"hash": "062ecf5d3e9f4c5d3e46f7c845b9224c"
			}
		],
		"previousHash": "0000183747554738bb613896b163f8b0",
		"timestamp": 1529519371219,
		"nonce": 17678,
		"hash": "0000ae56e0e2f69d9db37f57ea7d894d"
	},
	{
		"index": 118,
		"data": [
			{
				"from": "TcDNpLKPeZvrU25O",
				"to": "INYpp3IEuIvKX0SB",
				"amount": 2367,
				"timestamp": 1529519371620,
				"hash": "cfb174530b8a4a47b0ef71d04f03df6b"
			}
		],
		"previousHash": "0000ae56e0e2f69d9db37f57ea7d894d",
		"timestamp": 1529519371620,
		"nonce": 854,
		"hash": "0000e477f2b06789d5a7db4fa59a2f68"
	},
	{
		"index": 119,
		"data": [
			{
				"from": "sVYZvGCKOi4BaSdi",
				"to": "QaOccCI3zJYDwvK6",
				"amount": 8950,
				"timestamp": 1529519371659,
				"hash": "a5badbebd690f2f32e9914ef821b3aa3"
			}
		],
		"previousHash": "0000e477f2b06789d5a7db4fa59a2f68",
		"timestamp": 1529519371659,
		"nonce": 82369,
		"hash": "0000c986d2f64038a9ded4d2d7879514"
	},
	{
		"index": 120,
		"data": [
			{
				"from": "Z0qacmzVT2Y2D1Vh",
				"to": "T47Ok9bwe4dF1UsZ",
				"amount": 6734,
				"timestamp": 1529519373299,
				"hash": "9681e7f53d62d41ae1a13b0acfd7e06c"
			}
		],
		"previousHash": "0000c986d2f64038a9ded4d2d7879514",
		"timestamp": 1529519373299,
		"nonce": 54505,
		"hash": "0000f64bc0e29394aaf1c3aa164cea13"
	},
	{
		"index": 121,
		"data": [
			{
				"from": "YyzBGHWtwtlt2iEF",
				"to": "Prv5bHJuTEdwYZ90",
				"amount": 743,
				"timestamp": 1529519374566,
				"hash": "d4c3e2f543cbd223777af8b0e73bdd2b"
			}
		],
		"previousHash": "0000f64bc0e29394aaf1c3aa164cea13",
		"timestamp": 1529519374566,
		"nonce": 16718,
		"hash": "00000cfe2abd856ab7b0c0132edb059b"
	},
	{
		"index": 122,
		"data": [
			{
				"from": "ZcbfRjrECQMyfhGU",
				"to": "ua3V2ctKa0U2ydp9",
				"amount": 3895,
				"timestamp": 1529519375187,
				"hash": "61003240a58a201b3bf8a211477fa51a"
			}
		],
		"previousHash": "00000cfe2abd856ab7b0c0132edb059b",
		"timestamp": 1529519375187,
		"nonce": 28775,
		"hash": "000082ffdd0fa0561eeb68de040bd35a"
	},
	{
		"index": 123,
		"data": [
			{
				"from": "MDX7G611zOPiOFDR",
				"to": "mAbkPgNgRuBKZhHX",
				"amount": 5787,
				"timestamp": 1529519376005,
				"hash": "df59b2034b53a04b28cae8a9c769b5a8"
			}
		],
		"previousHash": "000082ffdd0fa0561eeb68de040bd35a",
		"timestamp": 1529519376005,
		"nonce": 28098,
		"hash": "00004293b4d38485d7b7b7e9dcd443b0"
	},
	{
		"index": 124,
		"data": [
			{
				"from": "jqnzp076uJJA5NqW",
				"to": "HJw52xNTvQ5vjDPR",
				"amount": 9045,
				"timestamp": 1529519376770,
				"hash": "5b4fdb587607890cfea7ca592643c4b9"
			}
		],
		"previousHash": "00004293b4d38485d7b7b7e9dcd443b0",
		"timestamp": 1529519376770,
		"nonce": 257038,
		"hash": "0000b3962b867dd956d264d0a5ae7cfa"
	},
	{
		"index": 125,
		"data": [
			{
				"from": "1hUzD1EjIieOtgrH",
				"to": "CzmEGIRSAUQabpc4",
				"amount": 3688,
				"timestamp": 1529519381533,
				"hash": "ce0525ec3ff92ff6ffbe6675a571f576"
			}
		],
		"previousHash": "0000b3962b867dd956d264d0a5ae7cfa",
		"timestamp": 1529519381533,
		"nonce": 22926,
		"hash": "000027e637360db8f8c5df52300149df"
	},
	{
		"index": 126,
		"data": [
			{
				"from": "hlOgHfuacCcBUylB",
				"to": "c6C6BldnqyD1jASz",
				"amount": 4193,
				"timestamp": 1529519382185,
				"hash": "58c4ccb56a7618a8beec1f2df73e17c3"
			}
		],
		"previousHash": "000027e637360db8f8c5df52300149df",
		"timestamp": 1529519382185,
		"nonce": 65707,
		"hash": "000095bdca3dd23fe9deb81c2eea6b89"
	},
	{
		"index": 127,
		"data": [
			{
				"from": "meJZhW1mjZRF018A",
				"to": "XffEUs90m4JozpAE",
				"amount": 4823,
				"timestamp": 1529519383468,
				"hash": "9088a617ed6a25e78adcfa834ce8fb74"
			}
		],
		"previousHash": "000095bdca3dd23fe9deb81c2eea6b89",
		"timestamp": 1529519383468,
		"nonce": 190433,
		"hash": "000013cba36dba57ecf522c467927a82"
	},
	{
		"index": 128,
		"data": [
			{
				"from": "EWACOxpGXiMkkyA7",
				"to": "kFn0Zg9DDphbwnGE",
				"amount": 9368,
				"timestamp": 1529519387005,
				"hash": "2dd2a93e01dbdfe38a343af159d2787e"
			}
		],
		"previousHash": "000013cba36dba57ecf522c467927a82",
		"timestamp": 1529519387005,
		"nonce": 197210,
		"hash": "0000274449db6f349ce97578ada39fd3"
	},
	{
		"index": 129,
		"data": [
			{
				"from": "biduVGmjsWL1K1Q9",
				"to": "D6PXeZqK8g0DpSRY",
				"amount": 2260,
				"timestamp": 1529519390425,
				"hash": "7cb8b303b5e5e156e7ed6fd7714ce771"
			}
		],
		"previousHash": "0000274449db6f349ce97578ada39fd3",
		"timestamp": 1529519390425,
		"nonce": 8384,
		"hash": "0000cba965fad42691f3248ec7d71f64"
	},
	{
		"index": 130,
		"data": [
			{
				"from": "SfMiOrSsvqZFjk2P",
				"to": "Xr3atdMMVbUqnlhA",
				"amount": 7000,
				"timestamp": 1529519390659,
				"hash": "392cfcdccc71c27896544719ad2950f4"
			}
		],
		"previousHash": "0000cba965fad42691f3248ec7d71f64",
		"timestamp": 1529519390659,
		"nonce": 4102,
		"hash": "00008fb7274491589e5388fe28c8c9d3"
	},
	{
		"index": 131,
		"data": [
			{
				"from": "tZQOHciXvTno7QTG",
				"to": "PnhHaghBxcmOBOwi",
				"amount": 2025,
				"timestamp": 1529519390821,
				"hash": "eee6bd5c5cf9fd81d41b4d9d984158fa"
			}
		],
		"previousHash": "00008fb7274491589e5388fe28c8c9d3",
		"timestamp": 1529519390821,
		"nonce": 81519,
		"hash": "000057abc5c625e13cc4632f1ba26148"
	},
	{
		"index": 132,
		"data": [
			{
				"from": "gSafZmlUda4FpAEB",
				"to": "F5Qdldy7uDuLOKwh",
				"amount": 7881,
				"timestamp": 1529519392368,
				"hash": "9312732a93a1bc49cb5007e1f3d32809"
			}
		],
		"previousHash": "000057abc5c625e13cc4632f1ba26148",
		"timestamp": 1529519392368,
		"nonce": 101667,
		"hash": "0000ca5df44635c9ee8f6e968a87a3cf"
	},
	{
		"index": 133,
		"data": [
			{
				"from": "D7BwkRUuIOghitOc",
				"to": "o4N3Ql3348IfVkoY",
				"amount": 4472,
				"timestamp": 1529519394234,
				"hash": "d18a3e3d2263a6ee7bb8eb7b8987f2b7"
			}
		],
		"previousHash": "0000ca5df44635c9ee8f6e968a87a3cf",
		"timestamp": 1529519394235,
		"nonce": 22320,
		"hash": "000086d11be553c17168d1c1802de13a"
	},
	{
		"index": 134,
		"data": [
			{
				"from": "0uQJgks3tCLd73Xs",
				"to": "ccQN2AIp2oceoX4O",
				"amount": 5084,
				"timestamp": 1529519394735,
				"hash": "ecef9c7e5715889801333d06e560f7f6"
			}
		],
		"previousHash": "000086d11be553c17168d1c1802de13a",
		"timestamp": 1529519394735,
		"nonce": 7170,
		"hash": "00009ff5459111c185b2e79525237b68"
	},
	{
		"index": 135,
		"data": [
			{
				"from": "MPTohTCbLh0ANsJh",
				"to": "btuq1eueUuhsQh1B",
				"amount": 7301,
				"timestamp": 1529519394920,
				"hash": "32e28c5678fdcdca0d95475653c2e817"
			}
		],
		"previousHash": "00009ff5459111c185b2e79525237b68",
		"timestamp": 1529519394920,
		"nonce": 33243,
		"hash": "000024b9cf5b7275e3c698eec8019d37"
	},
	{
		"index": 136,
		"data": [
			{
				"from": "9eXTt4SmqpbadKCh",
				"to": "D0GdUYKsXVfG4YbO",
				"amount": 1428,
				"timestamp": 1529519395508,
				"hash": "b18ce5f8a104157078ab9edcced2ea25"
			}
		],
		"previousHash": "000024b9cf5b7275e3c698eec8019d37",
		"timestamp": 1529519395508,
		"nonce": 7141,
		"hash": "0000462562e1fdebe73e078710a11b2b"
	},
	{
		"index": 137,
		"data": [
			{
				"from": "TKsTWFbnHy2IVEFO",
				"to": "P0rzImDpwMVp11ZM",
				"amount": 5108,
				"timestamp": 1529519395814,
				"hash": "8d2f1a0f425f95acf2e3ec69d12e48a9"
			}
		],
		"previousHash": "0000462562e1fdebe73e078710a11b2b",
		"timestamp": 1529519395814,
		"nonce": 32925,
		"hash": "0000921f5a175ec31fa18a704b3d7c09"
	},
	{
		"index": 138,
		"data": [
			{
				"from": "mNXDA3FjDaPVTgIX",
				"to": "GVulum3XYQ72W5jw",
				"amount": 7813,
				"timestamp": 1529519396671,
				"hash": "8ab3f51093dcfaac12bb41e14086047c"
			}
		],
		"previousHash": "0000921f5a175ec31fa18a704b3d7c09",
		"timestamp": 1529519396671,
		"nonce": 19853,
		"hash": "00009f85e7ae51e091d352aa01258e8d"
	},
	{
		"index": 139,
		"data": [
			{
				"from": "4bNTeQA2bH8cf2Dk",
				"to": "fT6wUAS5eB0pD22S",
				"amount": 3534,
				"timestamp": 1529519397221,
				"hash": "5534048c1238caeaf65daca53f3adca3"
			}
		],
		"previousHash": "00009f85e7ae51e091d352aa01258e8d",
		"timestamp": 1529519397221,
		"nonce": 396181,
		"hash": "00007c494fe3dc78e4d9bd6910aee034"
	},
	{
		"index": 140,
		"data": [
			{
				"from": "HWg729wCHToECsOw",
				"to": "DYSqLWbn2jX1YybC",
				"amount": 9468,
				"timestamp": 1529519404202,
				"hash": "94a49d9b4c3a1242c3c79b5e3a67dc0c"
			}
		],
		"previousHash": "00007c494fe3dc78e4d9bd6910aee034",
		"timestamp": 1529519404202,
		"nonce": 105594,
		"hash": "0000cbc900347688606c6ab536cdf11e"
	},
	{
		"index": 141,
		"data": [
			{
				"from": "175Ym3OFNE5wcDWW",
				"to": "6m8SWtmdXRFK2gNE",
				"amount": 9518,
				"timestamp": 1529519406526,
				"hash": "2a81cbca59f8d60410eaaa3db7ee7a62"
			}
		],
		"previousHash": "0000cbc900347688606c6ab536cdf11e",
		"timestamp": 1529519406526,
		"nonce": 51857,
		"hash": "0000d8b4b62948a7944f45b70073c99c"
	},
	{
		"index": 142,
		"data": [
			{
				"from": "4YLzKz0VwOQr6Yqs",
				"to": "bvzz9UfTNOr8tQcZ",
				"amount": 6829,
				"timestamp": 1529519407716,
				"hash": "0e938d308bdd3256e412d976dad6d9a4"
			}
		],
		"previousHash": "0000d8b4b62948a7944f45b70073c99c",
		"timestamp": 1529519407717,
		"nonce": 101988,
		"hash": "0000c3c526e6273253ce37209884fc32"
	},
	{
		"index": 143,
		"data": [
			{
				"from": "S6pzUamqx4a3hLFg",
				"to": "Wvx1MaParTopGC3T",
				"amount": 3928,
				"timestamp": 1529519409933,
				"hash": "3d3002d0800f7000c6a144afa7d62a9f"
			}
		],
		"previousHash": "0000c3c526e6273253ce37209884fc32",
		"timestamp": 1529519409933,
		"nonce": 76362,
		"hash": "000021f53f6150223d1dd6b607a684f0"
	},
	{
		"index": 144,
		"data": [
			{
				"from": "s7Bke9Sk22RrCH2L",
				"to": "6CU3Ac7gUk5Ds1kq",
				"amount": 6903,
				"timestamp": 1529519411814,
				"hash": "39b62677802e49991600adb8e8dfcefa"
			}
		],
		"previousHash": "000021f53f6150223d1dd6b607a684f0",
		"timestamp": 1529519411814,
		"nonce": 7754,
		"hash": "000038b8026bf68b9b1a0f2da0d1e5c9"
	},
	{
		"index": 145,
		"data": [
			{
				"from": "E95fEZJNkVhq5fVb",
				"to": "zFQInJBru9G20qHu",
				"amount": 913,
				"timestamp": 1529519412109,
				"hash": "3fe05b7ba30fce8c2c289d827a28f9e9"
			}
		],
		"previousHash": "000038b8026bf68b9b1a0f2da0d1e5c9",
		"timestamp": 1529519412109,
		"nonce": 204804,
		"hash": "00004240cf487f1736500473dec1c4b3"
	},
	{
		"index": 146,
		"data": [
			{
				"from": "KhNrjw6xmDgjim2p",
				"to": "FqO6lVvJMaN5ElSS",
				"amount": 8229,
				"timestamp": 1529519417804,
				"hash": "02b12238e7df8add983e05addf619077"
			}
		],
		"previousHash": "00004240cf487f1736500473dec1c4b3",
		"timestamp": 1529519417804,
		"nonce": 32654,
		"hash": "0000ea7b20e8f4da838db6c5bdd67d6e"
	},
	{
		"index": 147,
		"data": [
			{
				"from": "7inKU1VGkEyDwMk3",
				"to": "Vi8hUfA67SKCwbtM",
				"amount": 5669,
				"timestamp": 1529519418628,
				"hash": "403f645cb296ed83bfc818ea4204835e"
			}
		],
		"previousHash": "0000ea7b20e8f4da838db6c5bdd67d6e",
		"timestamp": 1529519418628,
		"nonce": 27712,
		"hash": "0000a85cfa0dcdeef219520684adfcf4"
	},
	{
		"index": 148,
		"data": [
			{
				"from": "bL3qIQ94IjDSg1Z0",
				"to": "sJeuf0qpasaiaad0",
				"amount": 7419,
				"timestamp": 1529519419432,
				"hash": "8e47639e062697514798ba1075e6be78"
			}
		],
		"previousHash": "0000a85cfa0dcdeef219520684adfcf4",
		"timestamp": 1529519419432,
		"nonce": 9667,
		"hash": "0000aa2cabd8ddb2c39cbe6d873c2b4d"
	},
	{
		"index": 149,
		"data": [
			{
				"from": "7T4XL5OuHNH0THRa",
				"to": "LgONTGe2cCGS16MR",
				"amount": 4663,
				"timestamp": 1529519419728,
				"hash": "946d3f00b6658126dbc16ca1f7afc08a"
			}
		],
		"previousHash": "0000aa2cabd8ddb2c39cbe6d873c2b4d",
		"timestamp": 1529519419728,
		"nonce": 122152,
		"hash": "0000ffefa95e54f3df0acd7445db4d3d"
	},
	{
		"index": 150,
		"data": [
			{
				"from": "CGO5gJ9Uo0I3EZIs",
				"to": "QvRxdEmUBWvwAxWt",
				"amount": 7991,
				"timestamp": 1529519422076,
				"hash": "4cbced95981787dfbd0edbedde2fda69"
			}
		],
		"previousHash": "0000ffefa95e54f3df0acd7445db4d3d",
		"timestamp": 1529519422076,
		"nonce": 62789,
		"hash": "00001afd678f43b97e1ad40db4d923bd"
	}
]